tests/__init__.py
tests/conftest.py
tests/test_schema.py
tests/test_schema_manager.py
tf2schema/__init__.py
tf2schema/schema/__init__.py
tf2schema/schema/data.py
tf2schema/schema/manager.py
tf2schema/schema/schema.py
tf2schema/sku/__init__.py
tf2schema/sku/utils.py
tf2schema_py-0.4.6.dist-info/METADATA
tf2schema_py-0.4.6.dist-info/WHEEL
tf2schema_py-0.4.6.dist-info/top_level.txt
tf2schema_py-0.4.6.dist-info/RECORD
