Metadata-Version: 2.4
Name: tf2schema-py
Version: 0.4.6
Summary: A Python package to interact with the Team Fortress 2 Schema
Home-page: https://github.com/Osc44r/tf2schema/
Author: Osc44r
Keywords: Team Fortress 2,TF2,Steam,Schema,API
Classifier: Programming Language :: Python :: 3
Classifier: License :: OSI Approved :: MIT License
Classifier: Operating System :: OS Independent
Requires-Dist: httpx
Requires-Dist: python-dotenv
Requires-Dist: pytest
Requires-Dist: pytest-asyncio
Requires-Dist: fake-useragent
Requires-Dist: vdf
Dynamic: author
Dynamic: classifier
Dynamic: description
Dynamic: description-content-type
Dynamic: home-page
Dynamic: keywords
Dynamic: requires-dist
Dynamic: summary
